BorutaShap.py
BorutaShap-1.0.17.dist-info/LICENSE
BorutaShap-1.0.17.dist-info/METADATA
BorutaShap-1.0.17.dist-info/WHEEL
BorutaShap-1.0.17.dist-info/top_level.txt
BorutaShap-1.0.17.dist-info/RECORD
