Metadata-Version: 2.1
Name: BorutaShap
Version: 1.0.17
Summary: A feature selection algorithm.
Home-page: https://github.com/Ekeany/Boruta-Shap
Author: Eoghan Keany
Author-email: egnkeany@gmail.com
License: MIT
Platform: UNKNOWN
Classifier: License :: OSI Approved :: MIT License
Classifier: Programming Language :: Python :: 3
Classifier: Programming Language :: Python :: 3.7
Requires-Dist: scikit-learn
Requires-Dist: tqdm
Requires-Dist: statsmodels
Requires-Dist: matplotlib
Requires-Dist: pandas
Requires-Dist: numpy
Requires-Dist: shap (>=0.34.0)
Requires-Dist: seaborn
Requires-Dist: scipy
